verilog/behavioral_cla_ff/wrapfinal_tb.v



module cla (
    input [3:0] A,
    input [3:0] B, 
    output reg [4:0] F,
    input cin
    );
reg [3:0] g;
reg [3:0] p;
reg [4:0] ci;
 always @(*) begin
        ci[0]=cin;
        
        p[0] = A[0] ^ B[0]; g[0] = A[0] & B[0]; 
        p[1] = A[1] ^ B[1]; g[1] = A[1] & B[1];
        p[2] = A[2] ^ B[2]; g[2] = A[2] & B[2]; 
        p[3] = A[3] ^ B[3]; g[3] = A[3] & B[3]; 
        
        ci[1] = g[0] | (p[0] & ci[0]);
        ci[2] = g[1] | (p[1] & g[0]) | (p[1] & p[0] & ci[0]);
        ci[3] = g[2] | (p[2] & g[1]) | (p[2] & p[1] & g[0]) | (p[2] & p[1] & p[0] & ci[0]);
        ci[4] = g[3] | (p[3] & g[2]) | (p[3] & p[2] & g[1]) | (p[3] & p[2] & p[1] & g[0]) | (p[3] & p[2] & p[1] & p[0] & ci[0]);

        F[0]=p[0]^ci[0];
        F[1]=p[1]^ci[1];
        F[2]=p[2]^ci[2];
        F[3]=p[3]^ci[3];
        
        F[4] = ci[4];         
    end
endmodule

module input4_flip_flop(
	input [3:0]i,
	input clk,
    output reg [3:0]out);

always @(posedge clk)
    begin
		out <= i;
	end
endmodule

module input1_flip_flop(
	input i,
	input clk,
    output reg out);

always @(posedge clk)
    begin
		out <= i;
	end
endmodule

// `include "input4_flip_flop.v"
// `include "input1_flip_flop.v"
// `include "cla.v"


module wrap(
    input [3:0] a,
    input [3:0] b,
    input clk,
    input cin,
    output [4:0] c);
    wire [3:0] da;  
    wire [3:0] db;
    wire [4:0] df;
    input4_flip_flop da_inst (
        .i(a),
        .clk(clk),
        .out(da)
    ); 
    input4_flip_flop db_inst (
        .i(b),
        .clk(clk),
        .out(db)
    );
    input4_flip_flop sum (
        .i(df[3:0]),
        .clk(clk),
        .out(c[3:0])
    ); 
    input1_flip_flop carry (
        .i(df[4]),
        .clk(clk),
        .out(c[4])
    );
    cla cla_inst (
        .A(da),
        .B(db), 
        .F(df),
        .cin(cin)
    );
endmodule

module wrap_tb;
    reg [3:0] a;
    reg [3:0] b;
    reg clk;
    wire [4:0] c;
    reg cin;
 
    // Instantiate the wrap module
    wrap uut (
        .a(a),
        .b(b),
        .clk(clk),
        .c(c),
        .cin(cin)
    );

    // Clock generation
    initial begin
        clk = 0;
        forever #5 clk = ~clk;  // 10 ns period clock
    end

    integer i;

    // Test input stimulus
    initial begin
        for (i = 0; i < 10; i = i + 1)
        begin
            a = $random % 16;
            b = $random % 16;
            cin =  $random % 2;
            #10;  // Wait for results after each set of inputs
            $display("a = %d, b = %d,cin= %d, Sum (c) = %d", a, b, cin, c);
        end
        $finish;
    end

    //Dump waveform data
    initial begin
        $dumpfile("wrapfinal_tb.vcd");
        $dumpvars(0, wrap_tb);
    end
endmodule

verilog/behavioral_cla_ff/wrapfinal_tb.vcd
$date
	Wed Nov 20 14:47:58 2024
$end
$version
	Icarus Verilog
$end
$timescale
	1s
$end
$scope module wrap_tb $end
$var wire 5 ! c [4:0] $end
$var reg 4 " a [3:0] $end
$var reg 4 # b [3:0] $end
$var reg 1 $ cin $end
$var reg 1 % clk $end
$var integer 32 & i [31:0] $end
$scope module uut $end
$var wire 4 ' a [3:0] $end
$var wire 4 ( b [3:0] $end
$var wire 1 $ cin $end
$var wire 1 % clk $end
$var wire 5 ) df [4:0] $end
$var wire 4 * db [3:0] $end
$var wire 4 + da [3:0] $end
$var wire 5 , c [4:0] $end
$scope module carry $end
$var wire 1 % clk $end
$var wire 1 - i $end
$var reg 1 . out $end
$upscope $end
$scope module cla_inst $end
$var wire 1 $ cin $end
$var wire 4 / B [3:0] $end
$var wire 4 0 A [3:0] $end
$var reg 5 1 F [4:0] $end
$var reg 5 2 ci [4:0] $end
$var reg 4 3 g [3:0] $end
$var reg 4 4 p [3:0] $end
$upscope $end
$scope module da_inst $end
$var wire 1 % clk $end
$var wire 4 5 i [3:0] $end
$var reg 4 6 out [3:0] $end
$upscope $end
$scope module db_inst $end
$var wire 1 % clk $end
$var wire 4 7 i [3:0] $end
$var reg 4 8 out [3:0] $end
$upscope $end
$scope module sum $end
$var wire 1 % clk $end
$var wire 4 9 i [3:0] $end
$var reg 4 : out [3:0] $end
$upscope $end
$upscope $end
$upscope $end
$enddefinitions $end
#0
$dumpvars
bx :
bx 9
bx 8
b1 7
bx 6
b100 5
bx 4
bx 3
bx1 2
bx 1
bx 0
bx /
x.
x-
bx ,
bx +
bx *
bx )
b1 (
b100 '
b0 &
0%
1$
b1 #
b100 "
bx !
$end
#5
0-
b110 9
b110 )
b110 1
b11 2
b0 3
b101 4
b100 +
b100 0
b100 6
b1 *
b1 /
b1 8
1%
#10
0%
b1101 #
b1101 (
b1101 7
b11 "
b11 '
b11 5
b1 &
#15
1-
b1 9
b10001 )
b10001 1
b11111 2
b1 3
b1110 4
0.
b110 !
b110 ,
b110 :
b1101 *
b1101 /
b1101 8
b11 +
b11 0
b11 6
1%
#20
0%
b10 #
b10 (
b10 7
b101 "
b101 '
b101 5
b10 &
#25
0-
b1000 9
b1000 )
b1000 1
b1111 2
b0 3
b111 4
b101 +
b101 0
b101 6
b10 *
b10 /
b10 8
b1 :
b10001 !
b10001 ,
1.
1%
#30
0%
b110 #
b110 (
b110 7
b1101 "
b1101 '
b1101 5
b11 &
#35
1-
b100 9
b10100 )
b10100 1
b11111 2
b100 3
b1011 4
0.
b1000 !
b1000 ,
b1000 :
b110 *
b110 /
b110 8
b1101 +
b1101 0
b1101 6
1%
#40
0%
b1100 #
b1100 (
b1100 7
b100 &
#45
b1010 9
b11010 )
b11010 1
b11011 2
b1100 3
b1 4
b1100 *
b1100 /
b1100 8
b100 :
b10100 !
b10100 ,
1.
1%
#50
b1001 9
b11001 )
b11001 1
b11000 2
0%
0$
b101 #
b101 (
b101 7
b110 "
b110 '
b110 5
b101 &
#55
0-
b1011 9
b1011 )
b1011 1
b1000 2
b100 3
b11 4
b11001 !
b11001 ,
b1001 :
b101 *
b101 /
b101 8
b110 +
b110 0
b110 6
1%
#60
0%
b111 #
b111 (
b111 7
b101 "
b101 '
b101 5
b110 &
#65
b1100 9
b1100 )
b1100 1
b1110 2
b101 3
b10 4
b101 +
b101 0
b101 6
b111 *
b111 /
b111 8
b1011 :
b1011 !
b1011 ,
0.
1%
#70
0%
b10 #
b10 (
b10 7
b1111 "
b1111 '
b1111 5
b111 &
#75
1-
b1 9
b10001 )
b10001 1
b11100 2
b10 3
b1101 4
b1100 !
b1100 ,
b1100 :
b10 *
b10 /
b10 8
b1111 +
b1111 0
b1111 6
1%
#80
0%
b101 #
b101 (
b101 7
b1000 "
b1000 '
b1000 5
b1000 &
#85
0-
b1101 9
b1101 )
b1101 1
b0 2
b0 3
b1000 +
b1000 0
b1000 6
b101 *
b101 /
b101 8
b1 :
b10001 !
b10001 ,
1.
1%
#90
b1110 9
b1110 )
b1110 1
b11 2
0%
1$
b1101 #
b1101 (
b1101 7
b1101 "
b1101 '
b1101 5
b1001 &
#95
1-
b1011 9
b11011 )
b11011 1
b11011 2
b1101 3
b0 4
0.
b1110 !
b1110 ,
b1110 :
b1101 *
b1101 /
b1101 8
b1101 +
b1101 0
b1101 6
1%
#100
0%
b1010 &
